<?xml version="1.0" encoding="UTF-8"?><record_update>
    <sys_choice action="DELETE" field="u_request_type" table="x_58872_needit_needit" version="3">
        <sys_choice_set action="DELETE">
            <element>u_request_type</element>
            <name>x_58872_needit_needit</name>
            <sys_class_name/>
            <sys_created_by>admin</sys_created_by>
            <sys_created_on/>
            <sys_id>7cd0acd42fe6501019d6d7a72799b63b</sys_id>
            <sys_mod_count/>
            <sys_name>u_request_type</sys_name>
            <sys_package display_value="NeedIt" source="x_58872_needit">6ead8e780f603200cd674f8ce1050ed1</sys_package>
            <sys_policy/>
            <sys_scope display_value="NeedIt">6ead8e780f603200cd674f8ce1050ed1</sys_scope>
            <sys_update_name>sys_choice_x_58872_needit_needit_u_request_type</sys_update_name>
            <sys_updated_by>admin</sys_updated_by>
            <sys_updated_on>2020-08-06 13:42:46</sys_updated_on>
        </sys_choice_set>
        <sys_update_version action="INSERT_OR_UPDATE">
            <action>DELETE</action>
            <application/>
            <file_path/>
            <instance_id>99b25261db7f1f004f035d00cf961988</instance_id>
            <instance_name>dev69360</instance_name>
            <name>sys_choice_x_58872_needit_needit_u_request_type</name>
            <payload><![CDATA[<?xml version="1.0" encoding="UTF-8"?><record_update><sys_choice action="DELETE" field="u_request_type" table="x_58872_needit_needit" version="3"><sys_choice_set action="DELETE"><element>u_request_type</element><name>x_58872_needit_needit</name><sys_class_name/><sys_created_by/><sys_created_on/><sys_id/><sys_mod_count/><sys_name/><sys_package/><sys_policy/><sys_scope/><sys_update_name/><sys_updated_by/><sys_updated_on>2020-08-06 10:48:15</sys_updated_on></sys_choice_set></sys_choice></record_update>]]></payload>
            <payload_hash>1828161538</payload_hash>
            <record_name>x_58872_needit_needit.u_request_type</record_name>
            <reverted_from/>
            <source>64c0a8d42fe6501019d6d7a72799b692</source>
            <source_table>sys_update_set</source_table>
            <state>previous</state>
            <sys_created_by>admin</sys_created_by>
            <sys_created_on>2020-08-06 10:48:15</sys_created_on>
            <sys_id>a1c0e8d42fe6501019d6d7a72799b668</sys_id>
            <sys_mod_count>0</sys_mod_count>
            <sys_recorded_at>173c362bf640000001</sys_recorded_at>
            <sys_updated_by>admin</sys_updated_by>
            <sys_updated_on>2020-08-06 10:48:15</sys_updated_on>
            <type>Choice list</type>
            <update_guid>2dc0e8d47fe6501067794997adbd4d67</update_guid>
            <update_guid_history>2dc0e8d47fe6501067794997adbd4d67:1828161538,e5c0e8d467e65010c1b477b9a76cc564:1429053012,65c0e8d46be65010d0a79989d2990a61:-1514400100,4cd4501083e650100764580527b63c2f:0,33b45cdc7ca65010b2dff6b03b2fea5d:-1789633962,b3b45cdcc2a65010992bffe6f76f4e59:-1701966180,33b45cdc4ea65010f2a4ba29edcf4556:736548692,bfb45cdcfba65010afdbaa17e99ee252:833312879,c681e7fbc8da101007ef824993b6fa18:0,9f7127fbe5da10100e95b18357c7bb65:-697540987,137127fbbeda1010aa8aeac1ae6a4062:-1701966180,9f7127fb53da1010d2ea6da982c7d05e:736548692,1f7127fb83da101065749ab71c56565b:833312879,38ea536f315210104db090a61fce6b29:0,56da9f2f63521010aad6e679501f76e8:1828161538,12da9f2fe05210104b0edffb401d74e5:-103233526,9eda9f2fdb52101074340f8ef56170e1:-409579057,1eda9f2fb05210104414f6544d0f8bde:-1138527265,cb5dc3278a52101042f55e2904d5b3e5:195919578</update_guid_history>
        </sys_update_version>
        <sys_metadata_delete action="INSERT_OR_UPDATE">
            <sys_audit_delete/>
            <sys_class_name>sys_metadata_delete</sys_class_name>
            <sys_created_by>admin</sys_created_by>
            <sys_created_on>2020-08-06 10:48:32</sys_created_on>
            <sys_db_object display_value="" name="sys_choice_set">sys_choice_set</sys_db_object>
            <sys_id>7cd0acd42fe6501019d6d7a72799b63b</sys_id>
            <sys_metadata>7cd0acd42fe6501019d6d7a72799b63b</sys_metadata>
            <sys_mod_count>0</sys_mod_count>
            <sys_name>u_request_type</sys_name>
            <sys_package display_value="NeedIt" source="x_58872_needit">6ead8e780f603200cd674f8ce1050ed1</sys_package>
            <sys_parent/>
            <sys_policy/>
            <sys_scope display_value="NeedIt">6ead8e780f603200cd674f8ce1050ed1</sys_scope>
            <sys_scope_delete display_value="">94872a8897db403e8ee69a431de2fca4</sys_scope_delete>
            <sys_update_name>sys_choice_x_58872_needit_needit_u_request_type</sys_update_name>
            <sys_update_version display_value="sys_choice_x_58872_needit_needit_u_request_type">a1c0e8d42fe6501019d6d7a72799b668</sys_update_version>
            <sys_updated_by>admin</sys_updated_by>
            <sys_updated_on>2020-08-06 10:48:32</sys_updated_on>
        </sys_metadata_delete>
    </sys_choice>
    <sys_update_version action="INSERT_OR_UPDATE">
        <action>DELETE</action>
        <application display_value="NeedIt">6ead8e780f603200cd674f8ce1050ed1</application>
        <file_path/>
        <instance_id>99b25261db7f1f004f035d00cf961988</instance_id>
        <instance_name>dev69360</instance_name>
        <name>sys_choice_x_58872_needit_needit_u_request_type</name>
        <payload>&lt;?xml version="1.0" encoding="UTF-8"?&gt;&lt;record_update&gt;&lt;sys_choice action="DELETE" field="u_request_type" table="x_58872_needit_needit" version="3"&gt;&lt;sys_choice_set action="DELETE"&gt;&lt;element&gt;u_request_type&lt;/element&gt;&lt;name&gt;x_58872_needit_needit&lt;/name&gt;&lt;sys_class_name/&gt;&lt;sys_created_by&gt;admin&lt;/sys_created_by&gt;&lt;sys_created_on/&gt;&lt;sys_id&gt;7cd0acd42fe6501019d6d7a72799b63b&lt;/sys_id&gt;&lt;sys_mod_count/&gt;&lt;sys_name&gt;u_request_type&lt;/sys_name&gt;&lt;sys_package display_value="NeedIt" source="x_58872_needit"&gt;6ead8e780f603200cd674f8ce1050ed1&lt;/sys_package&gt;&lt;sys_policy/&gt;&lt;sys_scope display_value="NeedIt"&gt;6ead8e780f603200cd674f8ce1050ed1&lt;/sys_scope&gt;&lt;sys_update_name&gt;sys_choice_x_58872_needit_needit_u_request_type&lt;/sys_update_name&gt;&lt;sys_updated_by&gt;admin&lt;/sys_updated_by&gt;&lt;sys_updated_on&gt;2020-08-06 13:42:46&lt;/sys_updated_on&gt;&lt;/sys_choice_set&gt;&lt;sys_update_version action="INSERT_OR_UPDATE"&gt;&lt;action&gt;DELETE&lt;/action&gt;&lt;application/&gt;&lt;file_path/&gt;&lt;instance_id&gt;99b25261db7f1f004f035d00cf961988&lt;/instance_id&gt;&lt;instance_name&gt;dev69360&lt;/instance_name&gt;&lt;name&gt;sys_choice_x_58872_needit_needit_u_request_type&lt;/name&gt;&lt;payload&gt;&lt;![CDATA[&lt;?xml version="1.0" encoding="UTF-8"?&gt;&lt;record_update&gt;&lt;sys_choice action="DELETE" field="u_request_type" table="x_58872_needit_needit" version="3"&gt;&lt;sys_choice_set action="DELETE"&gt;&lt;element&gt;u_request_type&lt;/element&gt;&lt;name&gt;x_58872_needit_needit&lt;/name&gt;&lt;sys_class_name/&gt;&lt;sys_created_by/&gt;&lt;sys_created_on/&gt;&lt;sys_id/&gt;&lt;sys_mod_count/&gt;&lt;sys_name/&gt;&lt;sys_package/&gt;&lt;sys_policy/&gt;&lt;sys_scope/&gt;&lt;sys_update_name/&gt;&lt;sys_updated_by/&gt;&lt;sys_updated_on&gt;2020-08-06 10:48:15&lt;/sys_updated_on&gt;&lt;/sys_choice_set&gt;&lt;/sys_choice&gt;&lt;/record_update&gt;]]&gt;&lt;/payload&gt;&lt;payload_hash&gt;1828161538&lt;/payload_hash&gt;&lt;record_name&gt;x_58872_needit_needit.u_request_type&lt;/record_name&gt;&lt;reverted_from/&gt;&lt;source&gt;64c0a8d42fe6501019d6d7a72799b692&lt;/source&gt;&lt;source_table&gt;sys_update_set&lt;/source_table&gt;&lt;state&gt;previous&lt;/state&gt;&lt;sys_created_by&gt;admin&lt;/sys_created_by&gt;&lt;sys_created_on&gt;2020-08-06 10:48:15&lt;/sys_created_on&gt;&lt;sys_id&gt;a1c0e8d42fe6501019d6d7a72799b668&lt;/sys_id&gt;&lt;sys_mod_count&gt;0&lt;/sys_mod_count&gt;&lt;sys_recorded_at&gt;173c362bf640000001&lt;/sys_recorded_at&gt;&lt;sys_updated_by&gt;admin&lt;/sys_updated_by&gt;&lt;sys_updated_on&gt;2020-08-06 10:48:15&lt;/sys_updated_on&gt;&lt;type&gt;Choice list&lt;/type&gt;&lt;update_guid&gt;2dc0e8d47fe6501067794997adbd4d67&lt;/update_guid&gt;&lt;update_guid_history&gt;2dc0e8d47fe6501067794997adbd4d67:1828161538,e5c0e8d467e65010c1b477b9a76cc564:1429053012,65c0e8d46be65010d0a79989d2990a61:-1514400100,4cd4501083e650100764580527b63c2f:0,33b45cdc7ca65010b2dff6b03b2fea5d:-1789633962,b3b45cdcc2a65010992bffe6f76f4e59:-1701966180,33b45cdc4ea65010f2a4ba29edcf4556:736548692,bfb45cdcfba65010afdbaa17e99ee252:833312879,c681e7fbc8da101007ef824993b6fa18:0,9f7127fbe5da10100e95b18357c7bb65:-697540987,137127fbbeda1010aa8aeac1ae6a4062:-1701966180,9f7127fb53da1010d2ea6da982c7d05e:736548692,1f7127fb83da101065749ab71c56565b:833312879,38ea536f315210104db090a61fce6b29:0,56da9f2f63521010aad6e679501f76e8:1828161538,12da9f2fe05210104b0edffb401d74e5:-103233526,9eda9f2fdb52101074340f8ef56170e1:-409579057,1eda9f2fb05210104414f6544d0f8bde:-1138527265,cb5dc3278a52101042f55e2904d5b3e5:195919578&lt;/update_guid_history&gt;&lt;/sys_update_version&gt;&lt;sys_metadata_delete action="INSERT_OR_UPDATE"&gt;&lt;sys_audit_delete/&gt;&lt;sys_class_name&gt;sys_metadata_delete&lt;/sys_class_name&gt;&lt;sys_created_by&gt;admin&lt;/sys_created_by&gt;&lt;sys_created_on&gt;2020-08-06 10:48:32&lt;/sys_created_on&gt;&lt;sys_db_object display_value="" name="sys_choice_set"&gt;sys_choice_set&lt;/sys_db_object&gt;&lt;sys_id&gt;7cd0acd42fe6501019d6d7a72799b63b&lt;/sys_id&gt;&lt;sys_metadata&gt;7cd0acd42fe6501019d6d7a72799b63b&lt;/sys_metadata&gt;&lt;sys_mod_count&gt;0&lt;/sys_mod_count&gt;&lt;sys_name&gt;u_request_type&lt;/sys_name&gt;&lt;sys_package display_value="NeedIt" source="x_58872_needit"&gt;6ead8e780f603200cd674f8ce1050ed1&lt;/sys_package&gt;&lt;sys_parent/&gt;&lt;sys_policy/&gt;&lt;sys_scope display_value="NeedIt"&gt;6ead8e780f603200cd674f8ce1050ed1&lt;/sys_scope&gt;&lt;sys_scope_delete display_value=""&gt;94872a8897db403e8ee69a431de2fca4&lt;/sys_scope_delete&gt;&lt;sys_update_name&gt;sys_choice_x_58872_needit_needit_u_request_type&lt;/sys_update_name&gt;&lt;sys_update_version display_value="sys_choice_x_58872_needit_needit_u_request_type"&gt;a1c0e8d42fe6501019d6d7a72799b668&lt;/sys_update_version&gt;&lt;sys_updated_by&gt;admin&lt;/sys_updated_by&gt;&lt;sys_updated_on&gt;2020-08-06 10:48:32&lt;/sys_updated_on&gt;&lt;/sys_metadata_delete&gt;&lt;/sys_choice&gt;&lt;/record_update&gt;</payload>
        <payload_hash>-132910269</payload_hash>
        <record_name>x_58872_needit_needit.u_request_type</record_name>
        <reverted_from/>
        <source>a9cc201c2fe6501019d6d7a72799b692</source>
        <source_table>sys_update_set</source_table>
        <state>previous</state>
        <sys_created_by>admin</sys_created_by>
        <sys_created_on>2020-08-06 13:42:46</sys_created_on>
        <sys_id>0eb80ddc2f2a501019d6d7a72799b68e</sys_id>
        <sys_mod_count>0</sys_mod_count>
        <sys_recorded_at>173c402873d0000001</sys_recorded_at>
        <sys_updated_by>admin</sys_updated_by>
        <sys_updated_on>2020-08-06 13:42:46</sys_updated_on>
        <type>Choice list</type>
        <update_guid>86b80ddcd92a501039567d4f6bfdae8e</update_guid>
        <update_guid_history>86b80ddcd92a501039567d4f6bfdae8e:-132910269,0ab80ddc982a5010c03d0ce6d6e9088a:-1701966180,86b80ddc632a50109bd606ad5a065587:736548692,35b80ddc782a50102776a9d0c21b1d84:833312879,65d0acd4ade65010a7e8fbc85c60afeb:0,2dc0e8d47fe6501067794997adbd4d67:1828161538,e5c0e8d467e65010c1b477b9a76cc564:1429053012,65c0e8d46be65010d0a79989d2990a61:-1514400100,4cd4501083e650100764580527b63c2f:0,33b45cdc7ca65010b2dff6b03b2fea5d:-1789633962,b3b45cdcc2a65010992bffe6f76f4e59:-1701966180,33b45cdc4ea65010f2a4ba29edcf4556:736548692,bfb45cdcfba65010afdbaa17e99ee252:833312879,c681e7fbc8da101007ef824993b6fa18:0,9f7127fbe5da10100e95b18357c7bb65:-697540987,137127fbbeda1010aa8aeac1ae6a4062:-1701966180,9f7127fb53da1010d2ea6da982c7d05e:736548692,1f7127fb83da101065749ab71c56565b:833312879,38ea536f315210104db090a61fce6b29:0,56da9f2f63521010aad6e679501f76e8:1828161538,12da9f2fe05210104b0edffb401d74e5:-103233526,9eda9f2fdb52101074340f8ef56170e1:-409579057,1eda9f2fb05210104414f6544d0f8bde:-1138527265,cb5dc3278a52101042f55e2904d5b3e5:195919578</update_guid_history>
    </sys_update_version>
    <sys_metadata_delete action="INSERT_OR_UPDATE">
        <sys_audit_delete/>
        <sys_class_name>sys_metadata_delete</sys_class_name>
        <sys_created_by>admin</sys_created_by>
        <sys_created_on>2020-08-06 13:43:06</sys_created_on>
        <sys_db_object display_value="" name="sys_choice_set">sys_choice_set</sys_db_object>
        <sys_id>21c8cddc2f2a501019d6d7a72799b67d</sys_id>
        <sys_metadata>21c8cddc2f2a501019d6d7a72799b67d</sys_metadata>
        <sys_mod_count>0</sys_mod_count>
        <sys_name>u_request_type</sys_name>
        <sys_package display_value="NeedIt" source="x_58872_needit">6ead8e780f603200cd674f8ce1050ed1</sys_package>
        <sys_parent/>
        <sys_policy/>
        <sys_scope display_value="NeedIt">6ead8e780f603200cd674f8ce1050ed1</sys_scope>
        <sys_scope_delete display_value="">94872a8897db403e8ee69a431de2fca4</sys_scope_delete>
        <sys_update_name>sys_choice_x_58872_needit_needit_u_request_type</sys_update_name>
        <sys_update_version display_value="sys_choice_x_58872_needit_needit_u_request_type">0eb80ddc2f2a501019d6d7a72799b68e</sys_update_version>
        <sys_updated_by>admin</sys_updated_by>
        <sys_updated_on>2020-08-06 13:43:06</sys_updated_on>
    </sys_metadata_delete>
</record_update>
